examples/data/feature.geojson
examples/data/transformed_feature.geojson
geodeticengine/AuthBearerToken.py
geodeticengine/CoordTrans.py
geodeticengine/CrsSearch.py
geodeticengine/CtSearch.py
geodeticengine/MsalCredential.py
geodeticengine/__init__.py
geodeticengine/ege_api.py
geodeticengine/utils.py
tests/test_CoordTrans.py
geodeticengine-1.0.13.dist-info/METADATA
geodeticengine-1.0.13.dist-info/WHEEL
geodeticengine-1.0.13.dist-info/top_level.txt
geodeticengine-1.0.13.dist-info/RECORD
