Metadata-Version: 2.1
Name: geodeticengine
Version: 1.0.13
Summary: Library for transformation and conversion of coordinates used in Equinor.
Author-email: Equinor <peaar@equinor.com>
Maintainer-email: Per Helge Aarnes <peaar@equinor.com>, Torill Gabrielsen <tokjos@equinor.com>
Classifier: Programming Language :: Python :: 3.9
Requires-Python: >=3.9
Requires-Dist: msal
Requires-Dist: pyproj
Requires-Dist: python-dotenv
Requires-Dist: numpy
Requires-Dist: requests
Provides-Extra: dev
Requires-Dist: pytest ; extra == 'dev'
